Workbook

Sheet Assumptions
A1: Arbor — Financial Model
A2: Base case. Blue cells = editable inputs. All currency in € thousands (€000) unless noted /mo.
A3: v1.0 · 2026-06-07 · PAI / Arbor · companion to arbor-business-model-pricing-and-financials.md
B5: Y1 2026 | C5: Y2 2027 | D5: Y3 2028
A6: B2C — Consumer subscription
A7: Avg paying subscribers | B7: 1500 | C7: 9000 | D7: 38000
A8: Blended ARPU (€/mo) | B8: 11 | C8: 11 | D8: 11.5
A9: Fully-loaded COGS per paying user (€/mo) | B9: 1.4 | C9: 1.5 | D9: 1.6 | F9: AI (Claude+Gemini) + infra + Stripe
A10: Professional — seats
A11: Avg active seats | B11: 20 | C11: 140 | D11: 480
A12: Price per seat (€/mo) | B12: 45 | C12: 45 | D12: 45
A13: COGS per seat (€/mo) | B13: 4 | C13: 4 | D13: 4
A14: Institutional — B2B2C / B2G
A15: Avg active subsidised families | B15: 0 | C15: 1500 | D15: 12000
A16: ARPF (€/mo) | B16: 0 | C16: 5 | D16: 5.5
A17: Pilot & setup fees (€000/yr) | B17: 30 | C17: 30 | D17: 0 | F17: Fixed-fee cohort pilots
A18: Institutional COGS (% of recurring) | B18: 0.15 | C18: 0.15 | D18: 0.15
A19: Operating costs (€000)
A20: Team (loaded, NL/IL blend) | B20: 295 | C20: 750 | D20: 1600
A21: Sales & marketing | B21: 20 | C21: 180 | D21: 500
A22: Compliance / security / legal | B22: 30 | C22: 60 | D22: 120
A23: Content / expert review / localisation | B23: 25 | C23: 60 | D23: 150
A24: G&A / tooling / SaaS | B24: 15 | C24: 60 | D24: 130

Sheet Model
A1: Arbor — 3-Year P&L (€000)
A2: Black = formula · Green = link to Assumptions. Re-forecast monthly off real analytics.
B4: Y1 2026 | C4: Y2 2027 | D4: Y3 2028
A5: Revenue
A6: B2C subscription | B6: =Assumptions!B7*Assumptions!B8*12/1000 | C6: =Assumptions!C7*Assumptions!C8*12/1000 | D6: =Assumptions!D7*Assumptions!D8*12/1000
A7: Professional seats | B7: =Assumptions!B11*Assumptions!B12*12/1000 | C7: =Assumptions!C11*Assumptions!C12*12/1000 | D7: =Assumptions!D11*Assumptions!D12*12/1000
A8: Institutional recurring | B8: =Assumptions!B15*Assumptions!B16*12/1000 | C8: =Assumptions!C15*Assumptions!C16*12/1000 | D8: =Assumptions!D15*Assumptions!D16*12/1000
A9: Institutional pilot/setup fees | B9: =Assumptions!B17 | C9: =Assumptions!C17 | D9: =Assumptions!D17
A10: Total revenue | B10: =SUM(B6:B9) | C10: =SUM(C6:C9) | D10: =SUM(D6:D9)
A12: Cost of goods sold
A13: B2C COGS | B13: =Assumptions!B7*Assumptions!B9*12/1000 | C13: =Assumptions!C7*Assumptions!C9*12/1000 | D13: =Assumptions!D7*Assumptions!D9*12/1000
A14: Professional COGS | B14: =Assumptions!B11*Assumptions!B13*12/1000 | C14: =Assumptions!C11*Assumptions!C13*12/1000 | D14: =Assumptions!D11*Assumptions!D13*12/1000
A15: Institutional COGS | B15: =B8*Assumptions!B18 | C15: =C8*Assumptions!C18 | D15: =D8*Assumptions!D18
A16: Total COGS | B16: =SUM(B13:B15) | C16: =SUM(C13:C15) | D16: =SUM(D13:D15)
A17: Gross profit | B17: =B10-B16 | C17: =C10-C16 | D17: =D10-D16
A18: Gross margin % | B18: =B17/B10 | C18: =C17/C10 | D18: =D17/D10
A20: Operating expenses
A21: Team | B21: =Assumptions!B20 | C21: =Assumptions!C20 | D21: =Assumptions!D20
A22: Sales & marketing | B22: =Assumptions!B21 | C22: =Assumptions!C21 | D22: =Assumptions!D21
A23: Compliance / security / legal | B23: =Assumptions!B22 | C23: =Assumptions!C22 | D23: =Assumptions!D22
A24: Content / expert / localisation | B24: =Assumptions!B23 | C24: =Assumptions!C23 | D24: =Assumptions!D23
A25: G&A / tooling | B25: =Assumptions!B24 | C25: =Assumptions!C24 | D25: =Assumptions!D24
A26: Total OpEx | B26: =SUM(B21:B25) | C26: =SUM(C21:C25) | D26: =SUM(D21:D25)
A28: Profitability
A29: EBITDA | B29: =B17-B26 | C29: =C17-C26 | D29: =D17-D26
A30: EBITDA margin % | B30: =B29/B10 | C30: =C29/C10 | D30: =D29/D10
A31: Cumulative EBITDA (cash proxy) | B31: =B29 | C31: =B31+C29 | D31: =C31+D29
A33: Peak cumulative cash need (€000) | B33: =-MIN(B31:D31) | D33: Seed sizing carries buffer to €2.0–2.5M for slower institutional cycles.

Sheet Sensitivity
A1: Arbor — Year-3 Scenario Sensitivity (€000)
A2: Illustrative. Factor scales Y3 base revenue & COGS; OpEx held semi-fixed. Blue = input.
B4: Conservative | C4: Base | D4: Aggressive
A5: Revenue factor vs base | B5: 0.62 | C5: 1 | D5: 1.5
A6: Lever (driver) | B6: conv 4% / churn 7% | C6: conv 6% / churn 5.5% | D6: conv 8% + 2 muni deals
A7: Y3 revenue | B7: =Model!D10*B5 | C7: =Model!D10*C5 | D7: =Model!D10*D5
A8: Y3 COGS | B8: =Model!D16*B5 | C8: =Model!D16*C5 | D8: =Model!D16*D5
A9: Y3 OpEx (semi-fixed) | B9: =Model!D26 | C9: =Model!D26 | D9: =Model!D26
A10: Y3 EBITDA | B10: =B7-B8-B9 | C10: =C7-C8-C9 | D10: =D7-D8-D9
A11: Y3 EBITDA margin | B11: =B10/B7 | C11: =C10/C7 | D11: =D10/D7
